Workbook

Sheet Test Cases
A1: Murabaha Contractual Profit Protection – Test Scenarios (FRD Section 6)
A2: Baselines: see "Baselines" sheet. Current Status = status recorded in FRD 6.17. Fill columns M–R during execution.
A4: TC ID | B4: FRD Ref | C4: Area | D4: Scenario | E4: Type | F4: Baseline | G4: Preconditions | H4: Steps | I4: Test Data | J4: Expected Result | K4: Current Status (FRD) | L4: Priority | M4: Actual Result | N4: Result | O4: Defect ID | P4: Tester | Q4: Date | R4: Comments
A5: TC-01 | B5: 6.3 | C5: General servicing rule | D5: Permitted schedule changes keep contractual totals | E5: Positive | F5: B1 | G5: Executed Murabaha, 3 installments paid | H5: 1. Capture before/after: Cost Price, Contractual Profit, Selling Price, Profit Paid, Remaining Profit, Maturity Date, No. of installments. 2. Submit and approve a reschedule changing repayment date and extending by 2 installments. 3. Compare before/after. | I5: Reschedule from inst. 4; new date +15 days; extend +2 | J5: Dates, maturity, no. of installments and installment amounts change; allocation of remaining Cost Price and Profit changes. Invariant holds: Profit Paid + Remaining Profit = Contractual Profit (1,500.000); Selling Price = 11,500.000; Cost Price = 10,000.000. | K5: To be tested | L5: High | N5: Not Run
A6: TC-02 | B6: 6.3 | C6: General servicing rule | D6: Charges outside Profit do not change Selling Price | E6: Positive | F6: B1 | G6: Executed Murabaha with an overdue installment | H6: 1. Apply a late-payment charge. 2. Check outstanding obligation and Selling Price. | I6: Late charge BHD 10.000 | J6: Outstanding = outstanding Selling Price + 10.000 charge shown separately. Contractual Profit and Selling Price unchanged. | K6: To be tested | L6: High | N6: Not Run
A7: TC-03 | B7: 6.4 | C7: Passage of time & accrual | D7: Accrual across due dates (account current) | E7: Positive | F7: B1 | G7: Executed, all installments paid on time | H7: 1. Capture Contractual Profit. 2. Advance business date over 2 due dates, run accrual jobs. 3. Check cumulative accrued Profit. | I7: Business date +60 days | J7: Cumulative accrued Profit = scheduled Profit of elapsed periods; never above 1,500.000. Selling Price unchanged. | K7: PASS | L7: High | N7: Not Run
A8: TC-04 | B8: 6.4 | C8: Passage of time & accrual | D8: Accrual while significantly past due | E8: Positive | F8: B1 | G8: Executed, no repayments | H8: 1. Advance business date 90 days, run accrual jobs daily. 2. Check accrued Profit and total Profit. | I8: No payments for 90 days | J8: Accrued Profit follows the contractual schedule only; total Profit remains 1,500.000; no additional Profit for overdue days. | K8: PASS | L8: High | N8: Not Run
A9: TC-05 | B9: 6.4 | C9: Passage of time & accrual | D9: No Profit after maturity | E9: Positive | F9: B1 | G9: Executed, last 2 installments unpaid | H9: 1. Advance business date to maturity +30 days, then +90 days. 2. Run accrual jobs. 3. Check total and accrued Profit. | I9: Maturity +30 / +90 days | J9: No Profit accrues after maturity; cumulative accrued Profit ≤ 1,500.000; Selling Price unchanged. | K9: To be tested | L9: High | N9: Not Run
A10: TC-06 | B10: 6.4 | C10: Passage of time & accrual | D10: Accrual job re-run on the same date | E10: Negative | F10: B1 | G10: Executed | H10: 1. Run accrual job. 2. Re-run the same job for the same date. | I10: Same business date | J10: No duplicate accrual; accrued Profit identical after re-run. | K10: To be tested | L10: Medium | N10: Not Run
A11: TC-07 | B11: 6.4 | C11: Passage of time & accrual | D11: Full-term accrual equals Contractual Profit | E11: Positive | F11: B1 | G11: Executed, all installments paid on time to maturity | H11: 1. Run full lifecycle to closure. 2. Sum Profit recognized. | I11: 12 monthly installments | J11: Total Profit recognized = 1,500.000 exactly. | K11: To be tested | L11: High | N11: Not Run
A12: TC-08 | B12: 6.5 | C12: Partial repayment | D12: Payment below installment due | E12: Positive | F12: B1 | G12: Executed, installment 1 due 958.333 | H12: 1. Capture before/after: Cost Price, Contractual Profit, Selling Price, Profit Paid, Remaining Profit, Maturity Date, No. of installments. 2. Post repayment of 500.000 on due date. 3. Check allocation and totals. | I12: Repayment 500.000 | J12: Allocated per repayment strategy; no Profit recalculation; total Profit 1,500.000; remaining installment 1 balance 458.333. | K12: PASS | L12: High | N12: Not Run
A13: TC-09 | B13: 6.5 | C13: Partial repayment | D13: Several partial payments covering one installment | E13: Positive | F13: B1 | G13: Executed | H13: 1. Post 300.000, 300.000, 358.333 within the period. | I13: 3 payments | J13: Installment 1 fully paid; total Profit 1,500.000; no recalculation. | K13: To be tested | L13: Medium | N13: Not Run
A14: TC-10 | B14: 6.5 | C14: Partial repayment | D14: Prepayment above installment due | E14: Positive | F14: B1 | G14: Executed, installment 1 due | H14: 1. Capture before/after: Cost Price, Contractual Profit, Selling Price, Profit Paid, Remaining Profit, Maturity Date, No. of installments. 2. Post 2,000.000 on installment 1 due date. 3. Check schedule. | I14: Repayment 2,000.000 | J14: Installment 1 paid; excess 1,041.667 applied to future installments (or advance payment); Profit NOT recalculated on reduced balance; total Profit remains 1,500.000 (not reduced). | K14: To be tested | L14: High | N14: Not Run
A15: TC-11 | B15: 6.5 | C15: Partial repayment | D15: Prepayment covering several future installments | E15: Positive | F15: B1 | G15: Executed | H15: 1. Post 3 × 958.333 on installment 1 due date. | I15: 2,875.000 | J15: Installments 1–3 paid; remaining schedule and Profit unchanged; total Profit 1,500.000. | K15: To be tested | L15: Medium | N15: Not Run
A16: TC-12 | B16: 6.5 | C16: Partial repayment | D16: Partial repayment followed by delinquency | E16: Positive | F16: B1 | G16: Executed | H16: 1. Pay 500.000 on installment 1. 2. Advance 60 days without payment, run accruals. | I16: 500.000 then 60 days overdue | J16: Total Profit 1,500.000; no additional Profit for overdue period. | K16: PASS | L16: High | N16: Not Run
... A75: TC-71 | B75: 6.18 | C75: Core principle | D75: Invariant check across all servicing scenarios | E75: Positive | F75: B1, B2, B3 | G75: Run after each scenario above | H75: 1. For each executed scenario recompute Profit Paid + Remaining Profit. | I75: — | J75: Equals Contractual Profit at all times; Fixed Profit Amount (B1, B2) and Profit Rate (B3) both pass. | K75: To be tested | L75: High | N75: Not Run

Sheet Summary
A1: Execution summary
A3: FRD Ref | B3: Area | C3: Total | D3: Pass | E3: Fail | F3: Blocked | G3: Not Run | H3: GAP in FRD
A4: 6.3 | B4: General servicing rule | C4: =COUNTIF('Test Cases'!$B$5:$B$75,A4) -> 2 | D4: =COUNTIFS('Test Cases'!$B$5:$B$75,$A4,'Test Cases'!$N$5:$N$75,"Pass") -> 0 | E4: =COUNTIFS('Test Cases'!$B$5:$B$75,$A4,'Test Cases'!$N$5:$N$75,"Fail") -> 0 | F4: =COUNTIFS('Test Cases'!$B$5:$B$75,$A4,'Test Cases'!$N$5:$N$75,"Blocked") -> 0 | G4: =COUNTIFS('Test Cases'!$B$5:$B$75,$A4,'Test Cases'!$N$5:$N$75,"Not Run") -> 2 | H4: =COUNTIFS('Test Cases'!$B$5:$B$75,$A4,'Test Cases'!$K$5:$K$75,"GAP") -> 0
A5: 6.4 | B5: Passage of time & accrual | C5: =COUNTIF('Test Cases'!$B$5:$B$75,A5) -> 5 | D5: =COUNTIFS('Test Cases'!$B$5:$B$75,$A5,'Test Cases'!$N$5:$N$75,"Pass") -> 0 | E5: =COUNTIFS('Test Cases'!$B$5:$B$75,$A5,'Test Cases'!$N$5:$N$75,"Fail") -> 0 | F5: =COUNTIFS('Test Cases'!$B$5:$B$75,$A5,'Test Cases'!$N$5:$N$75,"Blocked") -> 0 | G5: =COUNTIFS('Test Cases'!$B$5:$B$75,$A5,'Test Cases'!$N$5:$N$75,"Not Run") -> 5 | H5: =COUNTIFS('Test Cases'!$B$5:$B$75,$A5,'Test Cases'!$K$5:$K$75,"GAP") -> 0
A6: 6.5 | B6: Partial repayment | C6: =COUNTIF('Test Cases'!$B$5:$B$75,A6) -> 6 | D6: =COUNTIFS('Test Cases'!$B$5:$B$75,$A6,'Test Cases'!$N$5:$N$75,"Pass") -> 0 | E6: =COUNTIFS('Test Cases'!$B$5:$B$75,$A6,'Test Cases'!$N$5:$N$75,"Fail") -> 0 | F6: =COUNTIFS('Test Cases'!$B$5:$B$75,$A6,'Test Cases'!$N$5:$N$75,"Blocked") -> 0 | G6: =COUNTIFS('Test Cases'!$B$5:$B$75,$A6,'Test Cases'!$N$5:$N$75,"Not Run") -> 6 | H6: =COUNTIFS('Test Cases'!$B$5:$B$75,$A6,'Test Cases'!$K$5:$K$75,"GAP") -> 0
A7: 6.6 | B7: Change repayment date | C7: =COUNTIF('Test Cases'!$B$5:$B$75,A7) -> 5 | D7: =COUNTIFS('Test Cases'!$B$5:$B$75,$A7,'Test Cases'!$N$5:$N$75,"Pass") -> 0 | E7: =COUNTIFS('Test Cases'!$B$5:$B$75,$A7,'Test Cases'!$N$5:$N$75,"Fail") -> 0 | F7: =COUNTIFS('Test Cases'!$B$5:$B$75,$A7,'Test Cases'!$N$5:$N$75,"Blocked") -> 0 | G7: =COUNTIFS('Test Cases'!$B$5:$B$75,$A7,'Test Cases'!$N$5:$N$75,"Not Run") -> 5 | H7: =COUNTIFS('Test Cases'!$B$5:$B$75,$A7,'Test Cases'!$K$5:$K$75,"GAP") -> 3
A8: 6.7 | B8: Mid-term grace | C8: =COUNTIF('Test Cases'!$B$5:$B$75,A8) -> 5 | D8: =COUNTIFS('Test Cases'!$B$5:$B$75,$A8,'Test Cases'!$N$5:$N$75,"Pass") -> 0 | E8: =COUNTIFS('Test Cases'!$B$5:$B$75,$A8,'Test Cases'!$N$5:$N$75,"Fail") -> 0 | F8: =COUNTIFS('Test Cases'!$B$5:$B$75,$A8,'Test Cases'!$N$5:$N$75,"Blocked") -> 0 | G8: =COUNTIFS('Test Cases'!$B$5:$B$75,$A8,'Test Cases'!$N$5:$N$75,"Not Run") -> 5 | H8: =COUNTIFS('Test Cases'!$B$5:$B$75,$A8,'Test Cases'!$K$5:$K$75,"GAP") -> 3
A9: 6.8 | B9: Extend / shorten period | C9: =COUNTIF('Test Cases'!$B$5:$B$75,A9) -> 5 | D9: =COUNTIFS('Test Cases'!$B$5:$B$75,$A9,'Test Cases'!$N$5:$N$75,"Pass") -> 0 | E9: =COUNTIFS('Test Cases'!$B$5:$B$75,$A9,'Test Cases'!$N$5:$N$75,"Fail") -> 0 | F9: =COUNTIFS('Test Cases'!$B$5:$B$75,$A9,'Test Cases'!$N$5:$N$75,"Blocked") -> 0 | G9: =COUNTIFS('Test Cases'!$B$5:$B$75,$A9,'Test Cases'!$N$5:$N$75,"Not Run") -> 5 | H9: =COUNTIFS('Test Cases'!$B$5:$B$75,$A9,'Test Cases'!$K$5:$K$75,"GAP") -> 0
A10: 6.9 | B10: Profit rate adjustment | C10: =COUNTIF('Test Cases'!$B$5:$B$75,A10) -> 4 | D10: =COUNTIFS('Test Cases'!$B$5:$B$75,$A10,'Test Cases'!$N$5:$N$75,"Pass") -> 0 | E10: =COUNTIFS('Test Cases'!$B$5:$B$75,$A10,'Test Cases'!$N$5:$N$75,"Fail") -> 0 | F10: =COUNTIFS('Test Cases'!$B$5:$B$75,$A10,'Test Cases'!$N$5:$N$75,"Blocked") -> 0 | G10: =COUNTIFS('Test Cases'!$B$5:$B$75,$A10,'Test Cases'!$N$5:$N$75,"Not Run") -> 4 | H10: =COUNTIFS('Test Cases'!$B$5:$B$75,$A10,'Test Cases'!$K$5:$K$75,"GAP") -> 0
A11: 6.10 | B11: Combined rescheduling | C11: =COUNTIF('Test Cases'!$B$5:$B$75,A11) -> 5 | D11: =COUNTIFS('Test Cases'!$B$5:$B$75,$A11,'Test Cases'!$N$5:$N$75,"Pass") -> 0 | E11: =COUNTIFS('Test Cases'!$B$5:$B$75,$A11,'Test Cases'!$N$5:$N$75,"Fail") -> 0 | F11: =COUNTIFS('Test Cases'!$B$5:$B$75,$A11,'Test Cases'!$N$5:$N$75,"Blocked") -> 0 | G11: =COUNTIFS('Test Cases'!$B$5:$B$75,$A11,'Test Cases'!$N$5:$N$75,"Not Run") -> 5 | H11: =COUNTIFS('Test Cases'!$B$5:$B$75,$A11,'Test Cases'!$K$5:$K$75,"GAP") -> 0
A12: 6.11 | B12: Reschedule after partial repayment | C12: =COUNTIF('Test Cases'!$B$5:$B$75,A12) -> 4 | D12: =COUNTIFS('Test Cases'!$B$5:$B$75,$A12,'Test Cases'!$N$5:$N$75,"Pass") -> 0 | E12: =COUNTIFS('Test Cases'!$B$5:$B$75,$A12,'Test Cases'!$N$5:$N$75,"Fail") -> 0 | F12: =COUNTIFS('Test Cases'!$B$5:$B$75,$A12,'Test Cases'!$N$5:$N$75,"Blocked") -> 0 | G12: =COUNTIFS('Test Cases'!$B$5:$B$75,$A12,'Test Cases'!$N$5:$N$75,"Not Run") -> 4 | H12: =COUNTIFS('Test Cases'!$B$5:$B$75,$A12,'Test Cases'!$K$5:$K$75,"GAP") -> 0
A13: 6.12 | B13: Late payment & delinquency | C13: =COUNTIF('Test Cases'!$B$5:$B$75,A13) -> 5 | D13: =COUNTIFS('Test Cases'!$B$5:$B$75,$A13,'Test Cases'!$N$5:$N$75,"Pass") -> 0 | E13: =COUNTIFS('Test Cases'!$B$5:$B$75,$A13,'Test Cases'!$N$5:$N$75,"Fail") -> 0 | F13: =COUNTIFS('Test Cases'!$B$5:$B$75,$A13,'Test Cases'!$N$5:$N$75,"Blocked") -> 0 | G13: =COUNTIFS('Test Cases'!$B$5:$B$75,$A13,'Test Cases'!$N$5:$N$75,"Not Run") -> 5 | H13: =COUNTIFS('Test Cases'!$B$5:$B$75,$A13,'Test Cases'!$K$5:$K$75,"GAP") -> 0
A14: 6.13 | B14: Early / full settlement | C14: =COUNTIF('Test Cases'!$B$5:$B$75,A14) -> 5 | D14: =COUNTIFS('Test Cases'!$B$5:$B$75,$A14,'Test Cases'!$N$5:$N$75,"Pass") -> 0 | E14: =COUNTIFS('Test Cases'!$B$5:$B$75,$A14,'Test Cases'!$N$5:$N$75,"Fail") -> 0 | F14: =COUNTIFS('Test Cases'!$B$5:$B$75,$A14,'Test Cases'!$N$5:$N$75,"Blocked") -> 0 | G14: =COUNTIFS('Test Cases'!$B$5:$B$75,$A14,'Test Cases'!$N$5:$N$75,"Not Run") -> 5 | H14: =COUNTIFS('Test Cases'!$B$5:$B$75,$A14,'Test Cases'!$K$5:$K$75,"GAP") -> 0
A15: 6.14 | B15: Reversal / correction | C15: =COUNTIF('Test Cases'!$B$5:$B$75,A15) -> 5 | D15: =COUNTIFS('Test Cases'!$B$5:$B$75,$A15,'Test Cases'!$N$5:$N$75,"Pass") -> 0 | E15: =COUNTIFS('Test Cases'!$B$5:$B$75,$A15,'Test Cases'!$N$5:$N$75,"Fail") -> 0 | F15: =COUNTIFS('Test Cases'!$B$5:$B$75,$A15,'Test Cases'!$N$5:$N$75,"Blocked") -> 0 | G15: =COUNTIFS('Test Cases'!$B$5:$B$75,$A15,'Test Cases'!$N$5:$N$75,"Not Run") -> 5 | H15: =COUNTIFS('Test Cases'!$B$5:$B$75,$A15,'Test Cases'!$K$5:$K$75,"GAP") -> 0
... A21: 6.18 | B21: Core principle | C21: =COUNTIF('Test Cases'!$B$5:$B$75,A21) -> 1 | D21: =COUNTIFS('Test Cases'!$B$5:$B$75,$A21,'Test Cases'!$N$5:$N$75,"Pass") -> 0 | E21: =COUNTIFS('Test Cases'!$B$5:$B$75,$A21,'Test Cases'!$N$5:$N$75,"Fail") -> 0 | F21: =COUNTIFS('Test Cases'!$B$5:$B$75,$A21,'Test Cases'!$N$5:$N$75,"Blocked") -> 0 | G21: =COUNTIFS('Test Cases'!$B$5:$B$75,$A21,'Test Cases'!$N$5:$N$75,"Not Run") -> 1 | H21: =COUNTIFS('Test Cases'!$B$5:$B$75,$A21,'Test Cases'!$K$5:$K$75,"GAP") -> 0
A22: Total | C22: =SUM(C4:C21) -> 71 | D22: =SUM(D4:D21) -> 0 | E22: =SUM(E4:E21) -> 0 | F22: =SUM(F4:F21) -> 0 | G22: =SUM(G4:G21) -> 71 | H22: =SUM(H4:H21) -> 6

Sheet Baselines
A1: Test baselines (FRD sections 5.2.1, 6)
A3: ID | B3: Description | C3: Product setup | D3: Cost Price | E3: Profit | F3: Selling Price | G3: Installments | H3: Notes
A4: B1 | B4: Fixed Profit Amount – Declining | C4: Islamic = Yes, Murabaha, Profit Input Type = Fixed Profit Amount, Profit Method = Declining, Lock Point = Disbursement | D4: 10,000.000 BHD | E4: 1,500.000 | F4: 11,500.000 | G4: 12 monthly × 958.333 (last 958.337) | H4: FRD case A. After 3 paid: Profit Paid 616.185, Remaining 883.815, outstanding Cost 7,741.186
A5: B2 | B5: Fixed Profit Amount – Flat | C5: Same as B1 with Profit Method = Flat | D5: 10,000.000 BHD | E5: 1,500.000 | F5: 11,500.000 | G5: 12 × (833.333 + 125.000), last 958.337 | H5: Repeat key 6.6–6.8 cases
A6: B3 | B6: Profit Rate (%) Murabaha | C6: Profit Input Type = Profit Rate; FRD validation loans | D6: As in FRD 6.6 / 6.7 tests | E6: USD 150.92 / USD 127.35 | F6: — | G6: As in FRD tests | H6: Reproduces the GAP cases
A7: B4 | B7: Conventional loan | C7: Non-Islamic product, same terms as B3 | D7: Same as B3 | E7: — | F7: — | G7: Same | H7: Regression – behaviour must stay as today
A8: B5 | B8: FRD 6.11 example | C8: Murabaha with Contractual Profit 150 | D8: — | E8: 150 | F8: — | G8: Any | H8: 30 Profit already paid
A10: Common check for every case: capture before/after Cost Price, Contractual Profit, Selling Price, Profit Paid, Remaining Profit, Maturity Date, No. of installments. Pass only if Profit Paid + Remaining Profit = Contractual Profit and conventional products are unchanged.
